{
  "$schema": "https://mintlify.com/docs.json",
  "theme": "mint",
  "name": "AlphaRelay",
  "colors": {
    "primary": "#2563EB",
    "light": "#3B82F6",
    "dark": "#1D4ED8"
  },
  "favicon": "/favicon.png",
  "navigation": {
    "tabs": [
      {
        "tab": "Documentation",
        "groups": [
          {
            "group": "Start Here",
            "pages": [
              "index",
              "alpharelay/plain-english",
              "alpharelay/guide-overview",
              "alpharelay/roles-and-devices",
              "alpharelay/field-vs-relay",
              "alpharelay/training-mission"
            ]
          },
          {
            "group": "Run a Mission",
            "pages": [
              "alpharelay/before-you-go-to-the-field",
              "alpharelay/start-field-mission",
              "alpharelay/start-relay-mission",
              "alpharelay/watch-in-mission-overwatch",
              "alpharelay/event-logging",
              "alpharelay/completing-a-mission"
            ]
          },
          {
            "group": "Review and Report",
            "pages": [
              "alpharelay/footage-upload",
              "alpharelay/footage-playback",
              "alpharelay/report-generation",
              "alpharelay/evidence-sealing",
              "alpharelay/export-offline-package"
            ]
          },
          {
            "group": "Admin Setup",
            "pages": [
              "alpharelay/dashboard-account-organization",
              "alpharelay/one-time-setup",
              "alpharelay/security-privacy-ai-processing",
              "alpharelay/minimum-requirements"
            ]
          },
          {
            "group": "Help",
            "pages": [
              "alpharelay/troubleshooting",
              "alpharelay/connectivity-guide",
              "alpharelay/known-limitations",
              "alpharelay/glossary"
            ]
          }
        ]
      }
    ],
    "global": {
      "anchors": [
        {
          "anchor": "AlphaRelay",
          "href": "https://www.alpha-relay.com",
          "icon": "globe"
        }
      ]
    }
  },
  "logo": {
    "light": "/logo/alpharelay.png",
    "dark": "/logo/alpharelay.png"
  },
  "navbar": {
    "links": [
      {
        "label": "Open AlphaRelay",
        "href": "https://www.alpha-relay.com"
      }
    ]
  },
  "contextual": {
    "options": ["copy", "view"]
  },
  "footer": {
    "socials": {}
  }
}
